{"note":"This file is an internal implementation detail to speed up HTML report generation. Its format can change at any time. You might be looking for the JSON report: https://coverage.rtfd.io/cmd.html#cmd-json","format":5,"version":"7.9.1","globals":"10eebe1ef0701b36483aad5be4f1d6ae","files":{"z_1888b61c1dd10548___init___py":{"hash":"2e3b3c30123e24ade9270365b8722284","index":{"url":"z_1888b61c1dd10548___init___py.html","file":"ovos_core/__init__.py","description":"","nums":{"precision":0,"n_files":1,"n_statements":7,"n_excluded":0,"n_missing":0,"n_branches":0,"n_partial_branches":0,"n_missing_branches":0}}},"z_1888b61c1dd10548___main___py":{"hash":"e805afced9f86198ae1e8d85d4323350","index":{"url":"z_1888b61c1dd10548___main___py.html","file":"ovos_core/__main__.py","description":"","nums":{"precision":0,"n_files":1,"n_statements":31,"n_excluded":0,"n_missing":31,"n_branches":0,"n_partial_branches":0,"n_missing_branches":0}}},"z_5b704781350e2a59___init___py":{"hash":"8090184f2f34100c0491fd84583b6279","index":{"url":"z_5b704781350e2a59___init___py.html","file":"ovos_core/intent_services/__init__.py","description":"","nums":{"precision":0,"n_files":1,"n_statements":1,"n_excluded":0,"n_missing":0,"n_branches":0,"n_partial_branches":0,"n_missing_branches":0}}},"z_5b704781350e2a59_converse_service_py":{"hash":"6eb1b5de86d83748da37b47e3d9109de","index":{"url":"z_5b704781350e2a59_converse_service_py.html","file":"ovos_core/intent_services/converse_service.py","description":"","nums":{"precision":0,"n_files":1,"n_statements":184,"n_excluded":0,"n_missing":96,"n_branches":0,"n_partial_branches":0,"n_missing_branches":0}}},"z_5b704781350e2a59_fallback_service_py":{"hash":"733ec39dc91afed0ece0557f7fa79044","index":{"url":"z_5b704781350e2a59_fallback_service_py.html","file":"ovos_core/intent_services/fallback_service.py","description":"","nums":{"precision":0,"n_files":1,"n_statements":94,"n_excluded":0,"n_missing":13,"n_branches":0,"n_partial_branches":0,"n_missing_branches":0}}},"z_5b704781350e2a59_service_py":{"hash":"dbbf5fd0eac5c7d7ecc7018f8799c58f","index":{"url":"z_5b704781350e2a59_service_py.html","file":"ovos_core/intent_services/service.py","description":"","nums":{"precision":0,"n_files":1,"n_statements":322,"n_excluded":0,"n_missing":117,"n_branches":0,"n_partial_branches":0,"n_missing_branches":0}}},"z_5b704781350e2a59_stop_service_py":{"hash":"bddbf67d62121695b51fe53e7a65baaa","index":{"url":"z_5b704781350e2a59_stop_service_py.html","file":"ovos_core/intent_services/stop_service.py","description":"","nums":{"precision":0,"n_files":1,"n_statements":149,"n_excluded":0,"n_missing":17,"n_branches":0,"n_partial_branches":0,"n_missing_branches":0}}},"z_1888b61c1dd10548_skill_installer_py":{"hash":"d012570fed6bb5d14709ed319d994989","index":{"url":"z_1888b61c1dd10548_skill_installer_py.html","file":"ovos_core/skill_installer.py","description":"","nums":{"precision":0,"n_files":1,"n_statements":186,"n_excluded":0,"n_missing":74,"n_branches":0,"n_partial_branches":0,"n_missing_branches":0}}},"z_1888b61c1dd10548_skill_manager_py":{"hash":"6908fb9943dbd24b1d6c6af346af3ece","index":{"url":"z_1888b61c1dd10548_skill_manager_py.html","file":"ovos_core/skill_manager.py","description":"","nums":{"precision":0,"n_files":1,"n_statements":301,"n_excluded":0,"n_missing":82,"n_branches":0,"n_partial_branches":0,"n_missing_branches":0}}},"z_1888b61c1dd10548_transformers_py":{"hash":"8ed9a5b95249929e6455ecac877dbf7a","index":{"url":"z_1888b61c1dd10548_transformers_py.html","file":"ovos_core/transformers.py","description":"","nums":{"precision":0,"n_files":1,"n_statements":132,"n_excluded":0,"n_missing":43,"n_branches":0,"n_partial_branches":0,"n_missing_branches":0}}},"z_1888b61c1dd10548_version_py":{"hash":"5cd99a58b10cd2fdb2e0a3762005fd93","index":{"url":"z_1888b61c1dd10548_version_py.html","file":"ovos_core/version.py","description":"","nums":{"precision":0,"n_files":1,"n_statements":17,"n_excluded":0,"n_missing":17,"n_branches":0,"n_partial_branches":0,"n_missing_branches":0}}}}}